pkl_github_actions_step_generator/__init__.py
pkl_github_actions_step_generator/action_parser.py
pkl_github_actions_step_generator/action_transformer.py
pkl_github_actions_step_generator/cli.py
pkl_github_actions_step_generator/constraint_provider.py
pkl_github_actions_step_generator/core.py
pkl_github_actions_step_generator/pkl_generator.py
pkl_github_actions_step_generator/templates/PklProject.pkl.jinja
pkl_github_actions_step_generator/templates/action.pkl.jinja
pkl_github_actions_step_generator-0.1.13.dist-info/LICENSE.md
pkl_github_actions_step_generator-0.1.13.dist-info/METADATA
pkl_github_actions_step_generator-0.1.13.dist-info/WHEEL
pkl_github_actions_step_generator-0.1.13.dist-info/entry_points.txt
pkl_github_actions_step_generator-0.1.13.dist-info/top_level.txt
pkl_github_actions_step_generator-0.1.13.dist-info/RECORD
