Metadata-Version: 2.1
Name: pkl_github_actions_step_generator
Version: 0.1.13
Summary: A simple CLI tool to generate a Pkl definition for a given action
Home-page: https://github.com/emilymclean/pkl-github-actions-step-generator
Author: Emily McLean
Author-email: emilymcleandeveloper@gmail.com
License: MIT
Keywords: cli
Classifier: Intended Audience :: Developers
Classifier: License :: OSI Approved :: MIT License
Classifier: Programming Language :: Python :: 3
Classifier: Programming Language :: Python :: 3.11
Requires-Python: >=3.11
License-File: LICENSE.md
Requires-Dist: click
Requires-Dist: pyyaml
Requires-Dist: jinja2
Requires-Dist: requests
